eyesaver/__init__.py
eyesaver/main.py
eyesaver-1.0.0.dist-info/entry_points.txt
eyesaver-1.0.0.dist-info/WHEEL
eyesaver-1.0.0.dist-info/METADATA
eyesaver-1.0.0.dist-info/RECORD
